pexams/__init__.py
pexams/analysis.py
pexams/correct_exams.py
pexams/generate_exams.py
pexams/layout.py
pexams/main.py
pexams/pexams.css
pexams/schemas.py
pexams/translations.py
pexams/utils.py
pexams/assets/sample_test.json
pexams/assets/sample_test.md
pexams/assets/test_image.jpg
pexams/io/gift_converter.py
pexams/io/md_converter.py
pexams/io/moodle_xml_converter.py
pexams/io/rexams_converter.py
pexams/io/wooclap_converter.py
pexams-0.8.0.dist-info/licenses/LICENSE
pexams-0.8.0.dist-info/METADATA
pexams-0.8.0.dist-info/WHEEL
pexams-0.8.0.dist-info/entry_points.txt
pexams-0.8.0.dist-info/top_level.txt
pexams-0.8.0.dist-info/RECORD
