Metadata-Version: 2.4
Name: pexams
Version: 0.8.0
Summary: A Python library for generating and correcting exams using Playwright and OpenCV.
Author: Oscar J. Pellicer-Valero
Project-URL: Homepage, https://github.com/OscarPellicer/pexams
Classifier: Programming Language :: Python :: 3
Classifier: Operating System :: OS Independent
Requires-Python: >=3.9
License-File: LICENSE
Requires-Dist: opencv-python
Requires-Dist: numpy
Requires-Dist: pdf2image
Requires-Dist: pydantic
Requires-Dist: Markdown
Requires-Dist: Faker
Requires-Dist: Pillow
Requires-Dist: playwright
Requires-Dist: matplotlib
Requires-Dist: pandas
Requires-Dist: tabulate
Requires-Dist: torch
Requires-Dist: torchvision
Requires-Dist: transformers
Requires-Dist: timm
Requires-Dist: pymdown-extensions
Requires-Dist: python-Levenshtein
Requires-Dist: pypdf
Dynamic: license-file
